pytvmaze/__init__.py
pytvmaze/endpoints.py
pytvmaze/exceptions.py
pytvmaze/tvmaze.py
pytvmaze-2.0.8.dist-info/DESCRIPTION.rst
pytvmaze-2.0.8.dist-info/METADATA
pytvmaze-2.0.8.dist-info/RECORD
pytvmaze-2.0.8.dist-info/WHEEL
pytvmaze-2.0.8.dist-info/metadata.json
pytvmaze-2.0.8.dist-info/top_level.txt
