Metadata-Version: 2.0
Name: pytvmaze
Version: 2.0.8
Summary: Python interface to the TV Maze API (www.tvmaze.com)
Home-page: https://github.com/srob650/pytvmaze
Author: Spencer Roberts
Author-email: pytvmaze@gmail.com
License: MIT
Keywords: python tv television tvmaze
Platform: UNKNOWN
Classifier: Development Status :: 5 - Production/Stable
Classifier: Intended Audience :: Developers
Classifier: License :: OSI Approved :: MIT License
Classifier: Programming Language :: Python :: 2.6
Classifier: Programming Language :: Python :: 2.7
Classifier: Programming Language :: Python :: 3.5
Requires-Dist: requests
